{
  "_description": "B737-800 SOP/QRH/Limitations knowledge base. Structured from publicly available FCOM/FCTM/QRH documentation. Each entry maps to training Q&A pairs.",
  "_version": "1.0",
  "_sources": [
    "B737-800 QRH (Quick Reference Handbook) — memory items & non-normal procedures",
    "B737-800 FCOM Vol.1 — operating limitations",
    "B737-800 FCTM — normal procedures & SOP flows",
    "B737-800 AMM — systems knowledge"
  ],

  "limitations": [
    {
      "id": "LIM-001",
      "title": "最大操作速度 Vmo/Mmo",
      "content": "Vmo：340 KIAS（海平面至26,000英尺）。Mmo：马赫0.82（26,000英尺至41,000英尺）。超速警告响起时必须立即减速。超速事件须记录在飞机技术记录本中。",
      "triggers": ["OVERSPEED"],
      "questions": [
        "B737-800的最大操作速度是多少？",
        "Vmo和Mmo分别是多少？",
        "超速了怎么办？",
        "340节是什么限制？"
      ],
      "short_answer": "Vmo 340节（26000英尺以下），Mmo 马赫0.82（26000英尺以上）。超速警告响起立即收油门减速，必要时放出减速板。"
    },
    {
      "id": "LIM-002",
      "title": "最大高度限制",
      "content": "最大使用高度：41,000英尺。最大起降高度：8,400英尺。巡航通常在FL330-FL370。",
      "triggers": [],
      "questions": [
        "B737-800最高能飞多高？",
        "最大使用高度是多少？",
        "巡航高度通常多少？"
      ],
      "short_answer": "最大使用高度41,000英尺（FL410），最大起降高度8,400英尺。典型巡航高度FL330-FL370。"
    },
    {
      "id": "LIM-003",
      "title": "起落架速度限制",
      "content": "起落架收上：235 KIAS。起落架收放中：270 KIAS / M0.82。起落架放下后最大操作速度：320 KIAS / M0.82。",
      "triggers": ["TOO_LOW_GEAR"],
      "questions": [
        "起落架放下后最大速度多少？",
        "放起落架的速度限制是多少？",
        "起落架操作速度是多少？"
      ],
      "short_answer": "起落架放下后最大320节，收放中270节，收起后235节。超速可能损坏起落架舱门。"
    },
    {
      "id": "LIM-004",
      "title": "襟翼速度限制",
      "content": "襟翼放出最大速度：270 KIAS / M0.82。襟翼收上最大速度：235 KIAS。襟翼放下后最大速度：340 KIAS / M0.82。襟翼1放出速度250节，襟翼5放出速度250节，襟翼10放出速度210节，襟翼15放出速度200节，襟翼25放出速度190节，襟翼30放出速度175节，襟翼40放出速度162节。",
      "triggers": ["TOO_LOW_FLAPS"],
      "questions": [
        "襟翼30的最大速度是多少？",
        "各种襟翼设置的速度限制？",
        "放襟翼的速度限制是什么？"
      ],
      "short_answer": "襟翼1/5：250节，襟翼10：210节，襟翼15：200节，襟翼25：190节，襟翼30：175节，襟翼40：162节。超速可能造成襟翼结构损坏。"
    },
    {
      "id": "LIM-005",
      "title": "最大重量限制",
      "content": "最大滑行重量：约172,500磅（78,217公斤）。最大起飞重量：约171,800磅（77,900公斤）。最大着陆重量：144,000磅（65,317公斤）。最大零燃油重量：约138,300磅（约62,700公斤）。具体数值视各航空公司和飞机构型而定。",
      "triggers": [],
      "questions": [
        "最大起飞重量是多少？",
        "最大着陆重量限制？",
        "B737-800最多多重？",
        "飞机超重了怎么办？"
      ],
      "short_answer": "最大起飞重量约171,800磅，最大着陆重量144,000磅。超重着陆需检查飞机结构并记录在技术记录本中。"
    },
    {
      "id": "LIM-006",
      "title": "发动机限制",
      "content": "最大N1：约98%（TOGA推力）。最大EGT：950°C（连续不超过5分钟）。正常巡航N1：约55-65%。慢车N1：约22%。滑油压力正常范围25-65 psi。滑油温度正常20-120°C。",
      "triggers": ["ENG_OVERHEAT", "OIL_PRESS_LOW"],
      "questions": [
        "发动机EGT最高多少度？",
        "N1的正常范围是多少？",
        "滑油压力多少正常？"
      ],
      "short_answer": "EGT最高950°C（不超过5分钟），N1最大约98%TOGA推力。滑油压力25-65psi，温度20-120°C为正常范围。"
    },
    {
      "id": "LIM-007",
      "title": "APU限制",
      "content": "APU最大EGT：760°C。APU使用高度限制：最大起动高度31,000英尺，最大使用高度41,000英尺。APU在地面可提供电源和气源。",
      "triggers": ["APU_FIRE"],
      "questions": [
        "APU的EGT限制是多少？",
        "APU火警怎么办？",
        "APU有什么限制？"
      ],
      "short_answer": "APU最大EGT 760°C，最高使用高度41,000英尺。APU火警时立即拉出APU灭火手柄，释放灭火瓶。"
    },
    {
      "id": "LIM-008",
      "title": "风限制",
      "content": "最大顺风起飞/着陆：10节（经批准机场15节）。最大侧风起飞/着陆：约35节（视跑道状况）。飞行中无限制。",
      "triggers": ["WINDSHEAR"],
      "questions": [
        "最大侧风限制是多少？",
        "顺风起降的限制？",
        "侧风着陆有什么要求？"
      ],
      "short_answer": "最大顺风起降10节（批准机场15节），最大侧风约35节。风切变条件下应立即执行风切变改出程序。"
    },
    {
      "id": "LIM-009",
      "title": "TAKEOFF REFERENCE SPEEDS",
      "content": "V1：决断速度，超过此速度必须继续起飞（即使发动机失效）。VR：抬轮速度，开始拉杆使飞机离地。V2：起飞安全速度，一发失效时至少保持此速度爬升。VREF：着陆参考速度，等于1.3倍失速速度（着陆构型）。VREF+5为进近目标速度。具体数值由FMC根据重量/温度/跑道条件计算。",
      "triggers": ["STALL", "OVERSPEED"],
      "questions": [
        "V1 VR V2是什么意思？",
        "V1是什么速度？",
        "VREF怎么确定的？",
        "起飞决断速度是什么？"
      ],
      "short_answer": "V1决断速度（超过必须继续起飞），VR抬轮速度，V2起飞安全速度（一发失效最小爬升速度），VREF着陆参考速度=1.3倍失速速度，进近目标VREF+5节。FMC根据重量/温度/跑道计算。"
    },
    {
      "id": "LIM-010",
      "title": "COLD WEATHER OPERATIONS",
      "content": "外界温度-40°C至+50°C均可运行。低温操作注意事项：燃油冰点Jet A-1为-47°C（长期高空巡航需监控燃油温度），发动机滑油在极低温下需预热。高温操作：超过40°C需检查起飞性能减载。高空巡航OAT通常在-50°C至-60°C。",
      "triggers": ["ICING_CONDITION"],
      "questions": [
        "最冷能飞多冷？",
        "燃油会不会结冰？",
        "高空温度多少？"
      ],
      "short_answer": "运行温度-40°C至+50°C。燃油冰点Jet A-1约-47°C，高空巡航燃油需监控温度不低于冰点。机翼和发动机防冰在OAT<10°C+可见水汽时开启。"
    },
    {
      "id": "LIM-011",
      "title": "AUTOPILOT LIMITATIONS",
      "content": "自动驾驶接通最低高度：起飞后400英尺AGL（A/P可接通）。自动驾驶断开最低高度：进近中精密进近50英尺AGL、非精密进近按航图。自动着陆（Autoland）需CAT III ILS设备+特殊机组资质+飞机设备认证，决断高度可低至50英尺或无决断高度。自动驾驶在严重颠簸时应断开。",
      "triggers": [],
      "questions": [
        "自动驾驶最低多高可以接通？",
        "自动着陆有什么要求？",
        "什么时候必须断开自动驾驶？"
      ],
      "short_answer": "A/P最低400英尺AGL接通。精密进近50英尺AGL须断开。严重颠簸或安定面失控时立即断开A/P。自动着陆需CAT III ILS+机组资质+飞机认证。"
    },
    {
      "id": "LIM-012",
      "title": "BRAKE ENERGY LIMITS",
      "content": "刹车能量限制：中止起飞（RTO）时刹车吸收巨大能量。RTO后刹车温度可能超过500°C，需冷却后方可再次起飞。刹车温度指示>300°C时不可起飞（有起落架着火风险）。着陆后刹车温度通常200-400°C，使用自动刹车可减少刹车磨损和温度峰值。",
      "triggers": [],
      "questions": [
        "刹车温度多高算危险？",
        "中断起飞后刹车会怎样？",
        "着陆后刹车温度多少正常？"
      ],
      "short_answer": "刹车温度>300°C不可起飞（起落架着火风险）。RTO后刹车可能超500°C需冷却。着陆后正常200-400°C。自动刹车可均匀分配刹车能量减少峰值温度。"
    }
  ],

  "memory_items": [
    {
      "id": "MEM-001",
      "title": "发动机火警/严重损坏（QRH 8.2）",
      "content": "记忆项目：1. 自动油门—断开。2. 推力手柄（受影响发动机）—确认→收光。3. 发动机起动手柄（受影响发动机）—确认→切断。4. 发动机灭火手柄（受影响发动机）—确认→拉出。5. 如果灭火手柄或ENG OVERHEAT灯仍亮：旋转至止动位并保持1秒。30秒后如仍亮，旋转至另一止动位保持1秒。",
      "triggers": ["MASTER_WARNING", "ENG_OVERHEAT"],
      "questions": [
        "发动机着火了怎么办？",
        "发动机火警的记忆项目是什么？",
        "发动机灭火手柄怎么操作？"
      ],
      "short_answer": "记忆项目：1.自动油门断开 2.确认并收光故障发推力手柄 3.确认并切断故障发起动手柄 4.确认并拉出灭火手柄 5.如灯仍亮旋转灭火手柄释放灭火瓶。"
    },
    {
      "id": "MEM-002",
      "title": "客舱高度警告/快速失压（QRH 2.1）",
      "content": "记忆项目：1. 戴上氧气面罩，调节器至100%。2. 建立机组通讯。3. 增压模式选择器—人工。4. 外流活门开关—按住关位至活门全关。5. 如果客舱高度不可控：旅客信号牌开启→旅客氧气启动→执行紧急下降检查单。",
      "triggers": ["CABIN_ALT_HIGH", "MASTER_WARNING"],
      "questions": [
        "客舱失压怎么办？",
        "座舱高度警告响了怎么办？",
        "紧急下降怎么执行？"
      ],
      "short_answer": "1.戴氧气面罩100% 2.建立通讯 3.增压模式选人工 4.外流活门关 5.如不可控→旅客信号+氧气启动→执行紧急下降至10000英尺。"
    },
    {
      "id": "MEM-003",
      "title": "紧急下降（QRH 0.1）",
      "content": "记忆项目：PF通过PA广播'客舱机组，紧急下降，紧急下降'。旅客信号牌—开。立即下降至最低安全高度或10,000英尺（取较高者）。发动机起动电门—连续。推力手柄—减至最小。减速板—飞行卡位。目标速度设为Mmo/Vmo。",
      "triggers": ["CABIN_ALT_HIGH"],
      "questions": [
        "怎么执行紧急下降？",
        "紧急下降的速度是多少？",
        "紧急下降下降到多高？"
      ],
      "short_answer": "旅客信号开，立即下降至最低安全高度或10000英尺，发动机起动电门连续位，推力减至最小，减速板飞行卡位，目标速度Mmo/Vmo。"
    },
    {
      "id": "MEM-004",
      "title": "APU火警（QRH 8.1）",
      "content": "记忆项目：1. APU灭火手柄—确认→拉出→旋转至止动位→保持1秒。2. APU电门—关断。如在地面，同时通知地面人员撤离。",
      "triggers": ["APU_FIRE", "MASTER_WARNING"],
      "questions": [
        "APU着火了怎么办？",
        "APU火警的记忆项目？",
        "APU灭火手柄怎么用？"
      ],
      "short_answer": "1.APU灭火手柄确认→拉出→旋转释放→保持1秒 2.APU电门关断。地面时通知人员撤离。"
    },
    {
      "id": "MEM-005",
      "title": "起飞构型警告",
      "content": "记忆项目：确保正确的起飞构型。检查：襟翼已设定起飞位（通常襟翼1或5）、安定面配平在绿区、减速板收上、停留刹车松开。",
      "triggers": ["TAKEOFF_CONFIG", "MASTER_CAUTION"],
      "questions": [
        "起飞构型警告响了怎么办？",
        "起飞前要检查什么构型？",
        "TAKEOFF CONFIG是什么？"
      ],
      "short_answer": "立即检查：襟翼已设定起飞位（襟翼1/5）、安定面配平绿区、减速板收上、停留刹车松开。纠正构型后警告自动消失。"
    },
    {
      "id": "MEM-006",
      "title": "着陆构型警告",
      "content": "记忆项目：确保正确的着陆构型。检查：起落架放下（3个绿灯）、襟翼设定着陆位（通常襟翼30或40）。低于500英尺AGL时如起落架未放下或襟翼不足25%，警告喇叭将连续响。",
      "triggers": ["TOO_LOW_GEAR", "TOO_LOW_FLAPS", "MASTER_WARNING"],
      "questions": [
        "着陆构型警告响了怎么办？",
        "着陆前襟翼设置多少？",
        "着陆构型需要检查什么？"
      ],
      "short_answer": "确保起落架放下3个绿灯亮，襟翼设定着陆位（襟翼30或40）。如构型不正确无法立即纠正，执行复飞。"
    },
    {
      "id": "MEM-007",
      "title": "发动机极限/喘振/失速（QRH 7.4）",
      "content": "记忆项目：1. 自动油门—断开。2. 推力手柄（受影响发动机）—确认→收至参数在限制内或手柄收光。不要急于切断发动机—先用推力手柄控制。",
      "triggers": ["ENG_OVERHEAT", "STALL", "MASTER_CAUTION"],
      "questions": [
        "发动机喘振了怎么办？",
        "发动机失速怎么处理？",
        "发动机参数超限怎么办？"
      ],
      "short_answer": "自动油门断开，确认并收故障发推力手柄至参数恢复正常或收光。先不急于切断发动机，用推力手柄控制是关键。"
    },
    {
      "id": "MEM-008",
      "title": "双发失去推力（QRH 7.6）",
      "content": "记忆项目：1. 发动机起动电门（两个）—飞行位。2. 发动机起动手柄（两个）—切断。3. EGT下降后：起动手柄→慢车位。4. 如EGT达950°C或30秒无增加：起动手柄→切断→再慢车，重复。",
      "triggers": ["MASTER_WARNING"],
      "questions": [
        "双发都失效了怎么办？",
        "双发停车怎么重新启动？",
        "双发失去推力记忆项目？"
      ],
      "short_answer": "起动电门飞行位→起动手柄切断→EGT下降后慢车→如EGT不增30秒重复切断→慢车循环。保持飞行速度建立风车转速辅助起动。"
    },
    {
      "id": "MEM-009",
      "title": "安定面失控（QRH 9.1）",
      "content": "记忆项目：1. 驾驶杆—用力稳住。2. 自动驾驶—断开（不要重新接通）。3. 自动油门—断开。4. 人工操纵俯仰。5. 如断开A/P后仍失控：安定面配平切断电门（两个）—切断。6. 如仍失控：安定面配平手轮—抓住并稳住。",
      "triggers": ["MASTER_WARNING"],
      "questions": [
        "安定面失控怎么办？",
        "飞机自动配平乱跑怎么办？"
      ],
      "short_answer": "用力稳住驾驶杆→A/P断开→A/T断开→人工操纵→如仍失控配平切断电门两个都切断→如仍失控抓住配平手轮稳住。"
    },
    {
      "id": "MEM-010",
      "title": "空速不可靠（QRH 10.1）",
      "content": "记忆项目：1. 自动驾驶—断开。2. 自动油门—断开。3. F/D电门（两个）—关断。4. 设定已知俯仰姿态和推力：襟翼放出时—10°俯仰/80% N1；襟翼收上时—4°俯仰/75% N1。",
      "triggers": ["WINDSHEAR", "STALL", "MASTER_CAUTION"],
      "questions": [
        "空速不可靠怎么办？",
        "空速表坏了怎么飞？"
      ],
      "short_answer": "A/P和A/T断开，F/D关断。襟翼放出10°俯仰+80% N1，襟翼收上4°俯仰+75% N1。以姿态+推力组合飞行，参照GPS地速。"
    },
    {
      "id": "MEM-011",
      "title": "SMOKE / FIRE / FUMES (QRH 8.7)",
      "content": "记忆项目：1. 氧气面罩—戴上，调节器100%。2. 机组通讯—建立。3. 烟雾/火源识别并隔离（关闭受影响的电气设备）。如烟源不明：驾驶舱门—开以检查客舱；空调组件—逐个关闭以隔离烟源；再循环风扇—关闭。如烟雾严重危及飞行安全：执行紧急下降并在最近机场着陆。",
      "triggers": ["MASTER_WARNING"],
      "questions": [
        "驾驶舱冒烟了怎么办？",
        "机上失火怎么处理？",
        "烟雾来源不明怎么排查？"
      ],
      "short_answer": "戴氧气面罩100%→建立通讯→隔离电门关闭可疑设备→如烟源不明逐个关PACK隔离→再循环风扇关。严重烟雾执行紧急下降→最近机场着陆。"
    },
    {
      "id": "MEM-012",
      "title": "单发进近和着陆",
      "content": "单发进近注意事项：1. 使用襟翼15作为着陆襟翼（比正常襟翼30/40提供更好的单发复飞性能）2. VREF按襟翼15计算（比襟翼30高约15-20节）3. 着陆距离增加约30% 4. 复飞时必须保持方向控制（偏航力矩大）5. 尽量使用最长跑道 6. 通知ATC宣布PAN PAN或MAYDAY（视情况）。",
      "triggers": ["MASTER_WARNING", "ENG_OVERHEAT"],
      "questions": [
        "单发着陆怎么飞？",
        "一个发动机坏了怎么着陆？",
        "单发着陆用什么襟翼？"
      ],
      "short_answer": "襟翼15着陆（单发复飞性能更好），VREF比正常高15-20节，着陆距离增加30%，用最长跑道，复飞注意方向控制。通知ATC PAN PAN / MAYDAY。"
    },
    {
      "id": "MEM-013",
      "title": "TCAS RA 避让程序",
      "content": "TCAS交通咨询（TA）和决断咨询（RA）：TA—目视搜索冲突飞机，做好RA准备。RA—立即响应！不要等待分析。按RA语音指令垂直机动（CLIMB/DESCEND等），同时通知ATC'TCAS RA'。RA解除后（CLEAR OF CONFLICT）回到原许可高度并通知ATC。飞行员对RA的响应优先于ATC指令。",
      "triggers": ["MASTER_CAUTION"],
      "questions": [
        "TCAS RA响了怎么应对？",
        "TCAS告警优先还是ATC指令优先？",
        "RA是什么？"
      ],
      "short_answer": "RA立即响应不等待！按RA语音垂直机动（爬升/下降），通知ATC'TCAS RA'。RA解除后回原高度。飞行员对RA的响应优先于ATC指令！"
    }
  ],

  "normal_sop": [
    {
      "id": "SOP-001",
      "title": "起飞前检查单",
      "content": "停留刹车—刹上。推力手柄—慢车。客舱—通知。襟翼—设定起飞位（绿色灯亮）。安定面配平—___单位设定。减速板—收上。飞行仪表—检查。发动机仪表—检查。起飞数据（V1/VR/V2）—交叉检查。自动刹车—RTO。着陆灯/频闪灯—开。皮托管加温—开。除冰—按需。应答机—TA/RA。起飞简令—完成。",
      "triggers": ["TAKEOFF_CONFIG"],
      "questions": [
        "起飞前检查单有哪些？",
        "起飞前要做什么准备？",
        "驾舱准备检查单？"
      ],
      "short_answer": "停留刹车刹上，襟翼设起飞位绿区，配平设定，起飞数据V1/VR/V2交叉检查，自动刹车RTO，着陆灯频闪灯开，皮托管加温开，应答机TA/RA，起飞简令完成。"
    },
    {
      "id": "SOP-002",
      "title": "下降/进近检查单",
      "content": "增压—着陆标高设定。RECALL—检查（核实琥珀色警戒灯）。自动刹车—设定（1/2/3/MAX）。着陆数据—VREF ___，决断高度/最低下降高度___。进近简令—完成。导航台—设置（ILS频率/航道）。高度表—设定并交叉检查。决断高度/最低下降高度—在PFD上设定。安全带信号—开。着陆灯—开。",
      "triggers": [],
      "questions": [
        "下降前要检查什么？",
        "进近检查单有哪些项目？",
        "进近准备要做哪些？"
      ],
      "short_answer": "增压着陆标高设定，RECALL检查，自动刹车设定，着陆数据VREF和决断高度交叉检查，导航台设置ILS，高度表交叉检查，安全带信号开，着陆灯开。"
    },
    {
      "id": "SOP-003",
      "title": "着陆检查单",
      "content": "客舱—最后通知。发动机起动电门—连续位。减速板—预位。起落架—放下（三个绿灯）。襟翼—设定着陆位（绿灯亮）。复飞高度—___英尺在MCP高度窗设定。在最后进近定位点（FAF）或下滑道截获时执行。",
      "triggers": ["TOO_LOW_GEAR", "TOO_LOW_FLAPS"],
      "questions": [
        "着陆检查单是什么？",
        "着陆前最后要检查什么？",
        "复飞高度设多少？"
      ],
      "short_answer": "客舱通知，发动机起动电门连续位，减速板预位，起落架放下3绿灯，襟翼着陆位设定，MCP设定复飞高度。这是最后构型确认。"
    },
    {
      "id": "SOP-004",
      "title": "复飞程序",
      "content": "1. 按压TOGA电门（或手动设定复飞推力）2. 宣布'复飞，襟翼___' 3. 带杆建立复飞姿态（15°俯仰）4. 证实正上升率 5. 按襟翼收上计划收襟翼 6. 按复飞航径飞行 7. 联系ATC报告复飞。复飞不是失败，是安全决定。",
      "triggers": ["PULL_UP", "GLIDESLOPE", "WINDSHEAR", "STALL"],
      "questions": [
        "复飞怎么执行？",
        "进近不稳定怎么办？",
        "复飞程序是什么？"
      ],
      "short_answer": "按压TOGA→宣布复飞→带杆15°俯仰→正上升率证实→按计划收襟翼→飞复飞航径→报告ATC。复飞是安全决定，不是失败。"
    },
    {
      "id": "SOP-005",
      "title": "发动机起动程序",
      "content": "1. APU气源接通（或地面气源）。2. 空调组件—关断。3. 发动机起动电门—地面位。4. N2转速达25%（或最大冷转转速）时：起动手柄—慢车位。5. 监控EGT上升（不超过950°C）和N1指示。6. EGT峰值后回落，N1稳定在~22%，起动完成。7. 发动机起动电门自动回中。",
      "triggers": ["ENG_OVERHEAT"],
      "questions": [
        "发动机怎么起动？",
        "起动发动机的步骤？"
      ],
      "short_answer": "APU气源接通，空调组件关，起动电门地面位，N2达25%时起动手柄慢车位，监控EGT不超过950°C，N1稳定约22%即完成。"
    },
    {
      "id": "SOP-006",
      "title": "稳定进近标准",
      "content": "在1,000英尺AGL（IMC）或500英尺AGL（VMC）必须建立稳定进近：飞机在正确航道上（下滑道/航向道一个点内），襟翼着陆位设定，起落架放下，推力稳定在进近推力范围，速度VREF+0至+20节，下降率不超过1,000fpm。任何参数不满足—执行复飞。",
      "triggers": ["SINK_RATE", "GLIDESLOPE"],
      "questions": [
        "什么是稳定进近？",
        "稳定进近的标准是什么？",
        "什么时候必须复飞？"
      ],
      "short_answer": "1000英尺AGL（仪表）或500英尺AGL（目视）必须稳定：航道一个点内，起落架放下襟翼着陆位，速度VREF+0至+20节，下降率不超过1000fpm。不满足即复飞。"
    },
    {
      "id": "SOP-007",
      "title": "起飞后检查单",
      "content": "正上升率证实后：起落架—收上。襟翼—按计划收上（V2+15节收襟翼1，按襟翼速度限制逐级收上）。APU—按需关断。发动机起动电门—自动位。空调组件—按需接通。应答机—检查。着陆灯/频闪灯—按需。发动机仪表—检查（N1/EGT/FF/滑油正常）。",
      "triggers": [],
      "questions": [
        "起飞后要做什么？",
        "起飞后检查单有哪些？",
        "起飞后什么时候收襟翼？"
      ],
      "short_answer": "正上升率后→收起落架→按V2+15收襟翼1（逐级收上）→APU按需关→起动电门自动位→应答机检查→灯光按需→发动机仪表检查正常。"
    },
    {
      "id": "SOP-008",
      "title": "关车检查单",
      "content": "停留刹车—刹上。APU—起动（如需）。发动机起动手柄（两个）—切断。发动机完全停转后：防撞灯—按需关。燃油泵—按需关。空调组件—按需关。应答机—关/STBY。电气地面电源—建立（如需）。停留刹车按需保持。驾驶舱检查—无异常灯光。",
      "triggers": [],
      "questions": [
        "关车检查单是什么？",
        "落地后怎么关发动机？",
        "飞机停好后的程序？"
      ],
      "short_answer": "停留刹车刹上→APU起动→发动机起动手柄切断→防撞灯按需→燃油泵按需关→应答机关/STBY→建立地面电源→驾驶舱检查无异常灯光。"
    },
    {
      "id": "SOP-009",
      "title": "起飞简令内容",
      "content": "起飞前PF向PM做起飞简令，内容：起飞跑道___，SID/离场程序___，初始高度___英尺，V1 __节/VR __节/V2 __节，襟翼设定___，发动机故障或火警时—V1前中断起飞/V1后继续起飞，紧急返场程序___，任何人有疑问或异常立即喊'STOP'。",
      "triggers": ["TAKEOFF_CONFIG"],
      "questions": [
        "起飞简令怎么说？",
        "起飞前PF要说什么？",
        "起飞简令包含哪些内容？"
      ],
      "short_answer": "跑道、离场程序、初始高度、V1/VR/V2速度、襟翼设定、一发失效预案（V1前STOP/V1后GO）、紧急返场程序。任何人有疑问立即喊STOP。"
    },
    {
      "id": "SOP-010",
      "title": "进近简令内容",
      "content": "进近前PF向PM做进近简令，内容：预计进近方式（ILS/RNAV/VOR等）___跑道___，ILS频率/航道___，决断高度/最低下降高度___英尺，复飞程序___，着陆襟翼___，自动刹车设定___，脱离跑道计划___，滑行路线___。特殊注意事项（地形/天气/NOTAM）。",
      "triggers": [],
      "questions": [
        "进近简令怎么说？",
        "进近前要讲什么？",
        "进近简令包含哪些内容？"
      ],
      "short_answer": "进近方式/跑道、ILS频率/航道、DA/MDA、复飞程序、襟翼设定、自动刹车、脱离跑道计划、滑行路线、特殊注意事项（地形/天气/NOTAM）。"
    }
  ],

  "systems": [
    {
      "id": "SYS-001",
      "title": "燃油系统",
      "content": "B737-800有三个油箱：左主油箱、右主油箱、中央油箱。总容量约6,875美制加仑（约46,000磅）。正常先用中央油箱油，再用主油箱油。燃油不平衡超过1,000磅需执行燃油平衡程序：打开交输供油活门，关闭油量高一侧燃油泵。低油量警告：低于约3,000磅时触发MASTER CAUTION。",
      "triggers": ["FUEL_IMBALANCE", "LOW_FUEL"],
      "questions": [
        "B737的油箱怎么分布？",
        "燃油不平衡了怎么办？",
        "总共有多少燃油？"
      ],
      "short_answer": "左主/右主/中央三个油箱，总容量约46,000磅。不平衡超1,000磅时打开交输活门、关高侧燃油泵平衡。低油量约3,000磅触发MASTER CAUTION。"
    },
    {
      "id": "SYS-002",
      "title": "液压系统",
      "content": "B737-800有A和B两套独立液压系统。每套系统标称压力3,000 psi，正常范围2,800-3,200 psi。A系统驱动：起落架收放、某些飞行操纵、1号反推。B系统驱动：起落架收放（备用）、某些飞行操纵、2号反推。还有备用液压系统和PTU（动力转换组件）。液压量正常>90%。",
      "triggers": [],
      "questions": [
        "液压系统有几套？",
        "液压压力多少正常？",
        "液压油漏光了怎么办？"
      ],
      "short_answer": "A/B两套独立液压系统，标称压力3,000 psi（2,800-3,200正常）。液压量>90%。A/B各驱动一半飞行操纵和一侧反推，互为备份。"
    },
    {
      "id": "SYS-003",
      "title": "电气系统",
      "content": "主电源：28V DC总线。电源来源：两台发动机驱动发电机（各~90KVA）、APU发电机、地面电源、电瓶。正常飞行中两台发电机并联供电，总线电压28±4V。单发电机失效由另一台承担全机负载。APU发电机可替代任一发动机发电机。电瓶用于APU起动和应急电源（至少30分钟）。",
      "triggers": ["BUS_VOLT_ABNORM"],
      "questions": [
        "电源系统怎么工作的？",
        "电源电压异常怎么办？",
        "发电机失效了怎么办？"
      ],
      "short_answer": "28V DC系统。两台发动机发电机各~90KVA，APU发电机备用，电瓶30分钟应急。单发电机失效另一台带全负载。电压异常<24V或>32V检查发电机开关。"
    },
    {
      "id": "SYS-004",
      "title": "增压与空调系统",
      "content": "座舱增压来自发动机引气，经空调组件（PACK）调节温度和压力。正常座舱高度：巡航时6,500-7,000英尺。座舱压差：最大8.3 psi。座舱高度超过10,000英尺触发CABIN ALTITUDE警告（间歇喇叭+灯）。空调组件（两个）正常工作时控制座舱温度在18-30°C。",
      "triggers": ["CABIN_ALT_HIGH"],
      "questions": [
        "座舱增压怎么工作的？",
        "座舱高度多高算正常？",
        "增压系统失效了？"
      ],
      "short_answer": "发动机引气经PACK调节。巡航座舱高度6,500-7,000英尺，最大压差8.3psi。座舱高度超10,000英尺触发警告→执行紧急下降。"
    },
    {
      "id": "SYS-005",
      "title": "防冰系统",
      "content": "机翼防冰：使用发动机引气加热前缘缝翼。发动机防冰：加热发动机整流罩进气口。使用条件：OAT < 10°C且有可见水汽（云/雨/雪/雾），或OAT < 5°C且有跑道污染物。地上使用机翼防冰需发动机N1 > 65%。注意防冰会增加发动机引气消耗，导致可用推力下降。",
      "triggers": ["ICING_CONDITION"],
      "questions": [
        "什么时候开防冰？",
        "防冰系统怎么用？",
        "结冰条件是什么？"
      ],
      "short_answer": "OAT < 10°C+可见水汽或OAT < 5°C+跑道污染物时开启防冰。机翼防冰用引气加热前缘，发动机防冰加热整流罩。防冰会增加引气消耗降低推力。"
    },
    {
      "id": "SYS-006",
      "title": "近地警告系统 GPWS/EGPWS",
      "content": "GPWS提供7种基本警告模式：1-过大下降率 2-过大地形接近率 3-起飞后掉高度 4-不安全地形间隔（起落架未放下/襟翼未着陆位）5-低于下滑道过大 6-高度喊话（500,400,300,200,100,50,40,30,20,10英尺）7-风切变。EGPWS（增强型）增加了前视地形数据库、跑道数据库、前视地形告警。PULL UP是最严重告警，必须立即执行改出。",
      "triggers": ["PULL_UP", "TERRAIN", "SINK_RATE", "TOO_LOW_GEAR", "TOO_LOW_FLAPS", "GLIDESLOPE", "MINIMUMS"],
      "questions": [
        "GPWS有几种警告模式？",
        "PULL UP是什么级别的警告？",
        "GPWS和EGPWS有什么区别？"
      ],
      "short_answer": "GPWS有7种基本模式：过大下降率、地形接近、掉高度、不安全构型、下滑道偏离、高度喊话、风切变。EGPWS增加了前视地形数据库。PULL UP最严重，必须立即改出。"
    },
    {
      "id": "SYS-007",
      "title": "飞行控制系统",
      "content": "B737-800采用液压助力飞行控制系统。副翼（滚转）：每侧一个液压系统驱动。升降舵（俯仰）：A和B两套液压系统均可驱动，主用B系统。方向舵（偏航）：主用A系统。安定面配平：电动马达驱动（可人工手轮超控）。扰流板：飞行扰流板辅助滚转，地面扰流板用于减速。自动驾驶通过A/P伺服器驱动飞行控制。",
      "triggers": [],
      "questions": [
        "飞行控制怎么分配的？",
        "升降舵用哪个液压系统？",
        "方向舵用什么液压？"
      ],
      "short_answer": "副翼各用一侧液压，升降舵主用B系统（A备用），方向舵主用A系统。安定面配平电动+人工手轮超控。扰流板辅助滚转和减速。"
    },
    {
      "id": "SYS-008",
      "title": "起落架系统",
      "content": "起落架为前三点可收放式。主起落架向后内侧收起，前起落架向前收起。收放由A液压系统驱动（B系统备用）。应急放下：人工释放手柄使起落架自由下落到锁定位置（重力+气动+弹簧辅助）。起落架位置指示：三个绿色灯=放下锁定，红色灯=位置不一致或手柄与起落架位置不符。",
      "triggers": ["TOO_LOW_GEAR"],
      "questions": [
        "起落架怎么收放？",
        "起落架应急放下怎么做？",
        "三个绿灯是什么意思？"
      ],
      "short_answer": "前三点可收放，A液压驱动（B备用）。应急放下拉人工释放手柄，重力+气动辅助。三个绿灯=放下锁定。红灯=不一致或位置不符。低于500ft+起落架未放触发GPWS警告。"
    },
    {
      "id": "SYS-009",
      "title": "发动机 CFM56-7B 概述",
      "content": "CFM56-7B高涵道比涡扇发动机。推力等级：26,000磅（B737-800）。双转子：N1低压转子（风扇+低压涡轮），N2高压转子（高压压气机+高压涡轮）。N1 100%约为5,200 RPM，N2 100%约为15,000 RPM。附件齿轮箱：驱动发电机、液压泵、燃油泵、滑油泵等。FADEC全权数字发动机控制。",
      "triggers": ["ENG_OVERHEAT", "ENG_ASYM"],
      "questions": [
        "B737用的是什么发动机？",
        "CFM56推力多大？",
        "N1和N2分别是什么？"
      ],
      "short_answer": "CFM56-7B涡扇发动机，推力26,000磅。N1低压转子驱动风扇（5,200RPM满转），N2高压转子驱动压气机（15,000RPM满转）。FADEC全权数字控制，附件齿轮箱驱动发电机/液压泵/燃油泵。"
    },
    {
      "id": "SYS-010",
      "title": "自动油门 (A/T) 系统",
      "content": "A/T通过油门伺服马达自动调节推力。模式：N1模式（保持目标N1）、SPEED模式（保持目标速度）。起飞时A/T在84节自动进入THR HOLD直到800英尺。巡航中用FMC速度。进近时在约27英尺无线电高度自动收光油门。A/T可在任何时候人工超控。A/T LIM在单发或EEC降级时指示。",
      "triggers": [],
      "questions": [
        "自动油门怎么用？",
        "自动油门什么模式？",
        "自动油门什么时候断开？"
      ],
      "short_answer": "A/T有N1模式（恒推力）和SPEED模式（恒速）。起飞84节THR HOLD至800ft。巡航用FMC速度。进近27英尺自动收光。随时可人工超控。"
    }
  ],

  "sop_flows": [
    {
      "id": "FLOW-001",
      "title": "GPWS PULL UP 操作流程",
      "content": "PULL UP告警响起时立即执行：1. 断开自动油门和自动驾驶（如需满杆操纵）2. 将推力手柄推至最大推力（TOGA）3. 带杆建立并保持机头仰角15°（或抖杆器触发前最大限度）4. 收减速板（如已放出）5. 确认正上升率和高度增加 6. 起落架收上 7. 襟翼按计划逐步收上 8. 增速至最佳爬升速度 9. 告警停止后逐步恢复正常爬升。必须首先改变飞行路径，不要先分析原因。",
      "triggers": ["PULL_UP"],
      "questions": [
        "PULL UP响起后具体做什么？",
        "近地警告改出怎么做？",
        "听到PULL UP第一反应是什么？"
      ],
      "short_answer": "断开A/T和A/P→最大推力TOGA→带杆15°仰角→收减速板→证实正上升率→收起落架→收襟翼→增速爬升。先改变飞行路径，不要先分析原因。"
    },
    {
      "id": "FLOW-002",
      "title": "WINDSHEAR 改出流程",
      "content": "风切变警告响起或预测性风切变警告时：1. 立即按压TOGA电门 2. 保持当前襟翼和起落架构型（不改变）3. 按需操纵保持俯仰姿态（尽量15°）4. 不要追逐速度变化—以姿态飞行为主 5. 警告停止后缓慢恢复正常飞行。风切变改出时不可收襟翼和起落架—保持当前构型让飞机处于最稳定状态。",
      "triggers": ["WINDSHEAR"],
      "questions": [
        "遭遇风切变怎么改出？",
        "WINDSHEAR告警怎么办？",
        "风切变时能收襟翼吗？"
      ],
      "short_answer": "按压TOGA→保持当前襟翼和起落架构型不动→保持俯仰姿态尽量15°→不追逐速度变化→警告停止后缓慢恢复。风切变改出中不可收襟翼/起落架。"
    },
    {
      "id": "FLOW-003",
      "title": "STALL 失速改出流程",
      "content": "失速警告（抖杆器或STALL WARNING）时：1. 立即减小迎角—向前推杆至地平线以下 2. 推力手柄推至最大推力（TOGA）3. 收减速板（如已放出）4. 保持机翼水平（不要转弯）5. 等空速恢复后柔和带杆恢复爬升 6. 注意高度损失。失速改出先推杆减小迎角，再加油门—顺序不可颠倒。",
      "triggers": ["STALL"],
      "questions": [
        "飞机失速了怎么改出？",
        "失速警告响了怎么办？",
        "抖杆器动作了怎么做？"
      ],
      "short_answer": "先推杆减小迎角至地平线以下→TOGA推力→收减速板→保持机翼水平→空速恢复后柔和带杆爬升。先推杆再加油门，顺序不可颠倒。"
    },
    {
      "id": "FLOW-004",
      "title": "发动机火警 单发失效 后续流程",
      "content": "执行完记忆项目（8.2）后：隔离活门—关断。受影响侧PACK—关断。APU引气—关断。如可用起动APU。按需平衡燃油。应答机模式—TA ONLY（防止RA给出超单发性能的爬升指令）。火警解除后如需机翼防冰：隔离活门—自动。计划在最近合适机场着陆。单发进近和着陆需特别计算性能。",
      "triggers": ["ENG_OVERHEAT", "MASTER_WARNING"],
      "questions": [
        "发动机着火关车后还要做什么？",
        "单发着陆怎么准备？",
        "发动机火灾后续处理？"
      ],
      "short_answer": "隔离活门关→受影响PACK关→APU引气关→起动APU→平衡燃油→应答机TA ONLY→最近合适机场着陆。单发着陆需计算性能，注意进近速度修正。"
    },
    {
      "id": "FLOW-005",
      "title": "不安全地形间隔—构型警告 操作流程",
      "content": "当起落架未放下或襟翼未着陆位且低于500英尺AGL时GPWS发出构型警告。立即检查：1. 起落架手柄—放下位（确认3个绿灯）2. 襟翼手柄—着陆位（30或40，确认绿灯）3. 如果无法立即纠正构型（如卡阻）—执行复飞。不要带着不正确构型继续进近着陆。",
      "triggers": ["TOO_LOW_GEAR", "TOO_LOW_FLAPS"],
      "questions": [
        "TOO LOW GEAR警告怎么处理？",
        "起落架放不下来怎么办？",
        "着陆构型不完好怎么办？"
      ],
      "short_answer": "检查起落架手柄放下3绿灯→检查襟翼着陆位→如无法立即纠正（卡阻）→执行复飞。不要带不正确构型继续着陆。"
    },
    {
      "id": "FLOW-006",
      "title": "下滑道偏离—修正流程",
      "content": "GLIDESLOPE警告（CDI偏离>0.5个点，低于1,000英尺AGL时）：1. 检查ILS频率和航道设定正确 2. 检查高度表设定正确 3. 人工修正下滑道 4. 如果CDI偏离持续大于1个点或修正困难—立即执行复飞 5. 复飞后重新截获ILS或使用其他进近方式。低于1,000英尺不稳定进近必须复飞。",
      "triggers": ["GLIDESLOPE"],
      "questions": [
        "下滑道偏离了怎么修正？",
        "GLIDESLOPE警告怎么办？",
        "ILS下滑道飞偏了？"
      ],
      "short_answer": "检查ILS频率和航道→检查高度表→人工修正下滑道→如CDI持续>1点或难修正→立即复飞。低于1000英尺不稳定必须复飞。"
    },
    {
      "id": "FLOW-007",
      "title": "OVERSPEED 超速恢复流程",
      "content": "超速警告响起：1. 立即收油门（减小推力）2. 如有必要放出减速板至飞行卡位（注意减速板>320节不放出以免损坏）3. 保持当前俯仰姿态或柔和增加仰角以减速 4. 监控速度指示（IAS和MACH）5. 速度回至限制内后收减速板，重置推力。超速可能造成飞机结构损坏，必须及时纠正。",
      "triggers": ["OVERSPEED"],
      "questions": [
        "超速了怎么减速？",
        "超速警告响了怎么办？",
        "怎么快速减速？"
      ],
      "short_answer": "收油门→按需放减速板（不要超320节放）→柔和增仰角减速→监控IAS/MACH→速度回限制内后收减速板，重置推力。及时纠正避免结构损坏。"
    },
    {
      "id": "FLOW-008",
      "title": "低燃油处置流程",
      "content": "LOW FUEL告警（<约3,000磅）：1. 确认当前燃油量和消耗率 2. 计算续航时间和最近备降机场距离 3. 向ATC宣布MINIMUM FUEL或MAYDAY FUEL（视紧急程度）4. 执行燃油节约措施：降低巡航速度（远程巡航LRC）、减小N1、优先下降高度 5. 选择最近合适机场直飞备降 6. 监控发动机参数以防燃油耗尽熄火。",
      "triggers": ["LOW_FUEL", "MASTER_CAUTION"],
      "questions": [
        "燃油不够了怎么办？",
        "低燃油告警怎么处理？",
        "油量不足如何申请紧急？"
      ],
      "short_answer": "确认油量和消耗率→计算续航和备降距离→向ATC宣布MINIMUM FUEL或MAYDAY→执行节油措施（LRC巡航/减N1/优先下降）→直飞最近合适机场→监控发动机防熄火。"
    },
    {
      "id": "FLOW-009",
      "title": "电气系统故障处置流程",
      "content": "DRIVE灯亮或发电机失效：1. 检查受影响发电机 2. 如DRIVE灯亮—发电机驱动机构过热，须手动断开发电机以防卡死 3. 断开发电机电门 4. 负荷由另一台发电机+APU发电机（如运转）承担 5. 卸载非必要负载（厨房电源等）6. 如仅剩电瓶供电（双发电机+APU均失效）—电瓶供电约30分钟，立即着陆。",
      "triggers": ["BUS_VOLT_ABNORM", "MASTER_CAUTION"],
      "questions": [
        "发电机坏了怎么办？",
        "DRIVE灯亮了什么意思？",
        "电瓶能撑多久？"
      ],
      "short_answer": "DRIVE灯亮→手动断开发电机防卡死→另一发电机+APU承担负载→卸载非必要负载。仅电瓶供电约30分钟→立即着陆。双发电机+APU全失效是极端紧急情况。"
    },
    {
      "id": "FLOW-010",
      "title": "发动机起动失败处置（地面）",
      "content": "发动机起动中EGT快速上升接近950°C或N1不上升或N2悬挂不增速时：1. 起动手柄—切断（立即停止供油）2. 起动电门—地面位（冷转发动机驱散燃油蒸汽）3. 冷转30秒以上 4. 起动电门—关 5. 等待发动机冷却和排油（至少2分钟）6. 第二次起动尝试。如仍失败—叫机务。起动失败后必须充分冷转以防尾喷管内有残留燃油引起热起动或尾喷管着火。",
      "triggers": ["ENG_OVERHEAT"],
      "questions": [
        "发动机起动失败了怎么办？",
        "热起动怎么处理？",
        "EGT快超了怎么办？"
      ],
      "short_answer": "起动手柄立即切断→起动电门地面位冷转30秒驱散燃油→起动电门关→等2分钟冷却→第二次尝试。仍失败叫机务。必须充分冷转防尾喷着火。"
    },
    {
      "id": "FLOW-011",
      "title": "TCAS II 操作响应",
      "content": "TCAS II提供空中交通防撞功能：TA（Traffic Advisory）—提示有潜在冲突飞机，目视搜索并准备响应。RA（Resolution Advisory）—自动给出垂直避让指令。RA优先于ATC指令！响应：1. 立即按RA语音执行（CLIMB/INCREASE CLIMB/DESCEND等）2. 柔和但迅速地执行机动 3. 通知ATC 'TCAS RA' 4. RA解除后回到原许可。任何时候不逆RA指令操作。",
      "triggers": ["MASTER_CAUTION"],
      "questions": [
        "TCAS RA和TA有什么区别？",
        "RA指令怎么响应？",
        "TCAS RA时要不要听ATC的？"
      ],
      "short_answer": "TA提示搜索冲突飞机。RA垂直避让指令优先于ATC！立即执行RA指令→通知ATC 'TCAS RA'→RA解除回原高度。永远不逆RA操作。"
    },
    {
      "id": "FLOW-012",
      "title": "严重颠簸处置",
      "content": "遭遇严重颠簸：1. 旅客信号—开（通知客舱坐下系安全带）2. 自动驾驶/自动油门—保持接通（A/P在颠簸中比人工操纵更稳定）3. 速度设为颠簸穿透速度：约280 KIAS / M0.76（低于Vmo/Mmo但有结构安全余度）4. 保持机翼水平，不主动改变高度 5. 通知ATC要求改高度或改航避开颠簸区 6. 严重颠簸后检查飞机结构（目视检查+过载记录）。",
      "triggers": [],
      "questions": [
        "遇到严重颠簸怎么办？",
        "颠簸时速度该飞多少？",
        "颠簸中要不要断开自动驾驶？"
      ],
      "short_answer": "旅客信号开，A/P保持接通（比人工稳），速度280节/M0.76颠簸穿透速度，保持机翼水平不主动变高度，通知ATC改航避开。颠簸后检查飞机结构。"
    }
  ],

  "comms_weather": [
    {
      "id": "COMM-001",
      "title": "紧急通报 — MAYDAY",
      "content": "MAYDAY用于严重紧急情况（发动机火警、客舱失压、双发失效等构成迫在眉睫的危险）。呼叫格式：'MAYDAY MAYDAY MAYDAY，[呼号]，[飞机位置]，[紧急性质]，[机组意图]，[机上人数]，[剩余燃油磅数/小时]。' 应答机应设为7700。MAYDAY授予最高优先级，所有其他飞机将被要求避让。",
      "triggers": ["MASTER_WARNING"],
      "questions": [
        "MAYDAY怎么呼叫？",
        "什么时候喊MAYDAY？",
        "紧急情况怎么和ATC通报？"
      ],
      "short_answer": "MAYDAY×3，呼号，位置，紧急性质（发动机火警/失压等），意图（迫降/备降），机上人数，剩余燃油。应答机7700。MAYDAY=迫在眉睫的危险，ATC给予最高优先级。"
    },
    {
      "id": "COMM-002",
      "title": "紧急通报 — PAN PAN",
      "content": "PAN PAN用于紧急但不构成迫在眉睫危险的情况（如单发失效但飞机可控、燃油紧张、系统故障但可安全飞行）。呼叫格式：'PAN PAN PAN PAN PAN PAN，[呼号]，[位置]，[问题性质]，[意图]。' 应答机不必设为7700（维持原编码）。PAN PAN比MAYDAY低一级，ATC会给予优先处理但不要求其他飞机避让。",
      "triggers": ["MASTER_CAUTION", "LOW_FUEL", "ENG_ASYM"],
      "questions": [
        "PAN PAN怎么呼叫？",
        "PAN PAN和MAYDAY的区别？",
        "什么时候喊PAN PAN？"
      ],
      "short_answer": "PAN PAN×3，呼号，位置，问题性质（单发/低燃油/系统故障），意图。PAN PAN=紧急但不构成迫切危险，ATC优先处理。MAYDAY=迫在眉睫的危险必须立即援助，应答机7700。"
    },
    {
      "id": "COMM-003",
      "title": "应答机紧急编码",
      "content": "7500：非法干扰/劫机（HF—Hijack）。7600：通讯失效（RDO—Radio Out，76-76-No-Delay记住'七十六通不了'）。7700：紧急情况（EMG—Emergency，77级最高警告）。7700触发ATC雷达屏幕告警并自动通知相邻扇区。编码选择后雷达识别需约10-30秒。",
      "triggers": ["MASTER_WARNING"],
      "questions": [
        "应答机紧急编码有哪些？",
        "7700和7600什么区别？",
        "7500是什么意思？"
      ],
      "short_answer": "7500劫机/非法干扰，7600通讯失效，7700紧急情况。7700触发ATC雷达告警。7600记住'七十六通不了'。不要误设7500—会触发安保响应。"
    },
    {
      "id": "COMM-004",
      "title": "标准无线电通话结构",
      "content": "标准无线电通话：谁（呼号）→在哪（位置/高度）→干什么（意图/请求）。例如：'北京进近，白鹭8521，高度6000英尺保持，听你指挥。' 复诵（Readback）要求：管制指令必须全部复诵，特别是高度/航向/速度/跑道/应答机编码。遇疑问立即请求澄清'SAY AGAIN'。重要指令交叉检查后再执行。",
      "triggers": [],
      "questions": [
        "无线电怎么和管制说话？",
        "ATC指令要复诵吗？",
        "听不懂ATC怎么办？"
      ],
      "short_answer": "谁→在哪→干什么。管制指令必须复诵（高度/航向/速度/跑道/应答机）。听不懂说SAY AGAIN请求重复。重要指令交叉检查再执行。"
    },
    {
      "id": "WX-001",
      "title": "雷暴避让",
      "content": "雷暴（CB云）避让原则：1. 目视或雷达探测到CB云—绕飞！2. 侧向避让距离：FL350以上至少20海里，FL350以下至少10海里 3. 禁止从CB云下方飞行（可能有微下击暴流）4. CB云上方飞行需至少高于云顶5,000英尺（因对流和湍流）5. 不要试图穿透雷暴回波（雷达显示红/紫区）6. 绕飞时需通知ATC并申请偏航许可。",
      "triggers": ["WINDSHEAR"],
      "questions": [
        "遇到雷暴怎么绕？",
        "雷暴最少保持多少距离？",
        "能从雷暴下面飞吗？"
      ],
      "short_answer": "雷达或目视CB云→绕飞！侧向距离FL350以上≥20海里，以下≥10海里。禁飞CB云下方（微下击暴流风险）。上方≥5,000英尺。不要穿透红/紫回波。绕飞通知ATC申请偏航。"
    },
    {
      "id": "WX-002",
      "title": "微下击暴流 (Microburst) 识别与应对",
      "content": "微下击暴流是极端危险的低空风切变现象（直径<4公里，持续5-15分钟）。识别线索：雷暴底部有雨幡、地面扬尘环、闪电频繁。飞行中的迹象：IAS突然增加（逆风→顺风切换前的瞬态）然后急剧下降+大幅下沉率。应对：1. 低空遭遇立即TOGA+保持构型不动 2. 不要试图从中拉起—可能没有足够能量 3. 优先保持姿态 4. 如果IAS下降>30节且下沉率>2,000fpm—这是危及生命的信号。",
      "triggers": ["WINDSHEAR", "PULL_UP"],
      "questions": [
        "微下击暴流是什么？",
        "遇到微下击暴流怎么办？",
        "怎么识别微下击暴流？"
      ],
      "short_answer": "雷暴低空极端下沉气流，直径<4km。识别：雨幡/地面扬尘/IAS骤变后急降+大幅下沉。应对：TOGA+保持构型+保持姿态。IAS降>30节+下沉>2000fpm危及生命，立即改出。"
    },
    {
      "id": "WX-003",
      "title": "火山灰遇险处置",
      "content": "火山灰对喷气发动机极具破坏性（融化后玻璃化覆盖涡轮叶片）。遭遇火山灰迹象：驾驶舱内出现烟/硫磺味、圣埃尔莫之火、发动机排气温度异常上升、空速管可能堵塞。应对：1. 立即180°转弯离开灰云（灰云可能延伸数百海里）2. 减小推力（降低发动机温度减少灰融化）3. 发动机起动电门—连续位 4. 尽快脱离灰云范围 5. 着陆后发动机必须内窥检查。",
      "triggers": ["ENG_OVERHEAT", "STALL"],
      "questions": [
        "遇到火山灰怎么办？",
        "火山灰对飞机有什么危害？",
        "怎么知道遇到火山灰了？"
      ],
      "short_answer": "180°转弯离开灰云→减推力→发动机起动电门连续位→尽快脱离灰区。火山灰融化后玻璃化损坏涡轮叶片。迹象：硫磺味/圣埃尔莫火/EGT异常。着陆后必须内窥检查发动机。"
    },
    {
      "id": "WX-004",
      "title": "严重积冰处置",
      "content": "严重积冰（结冰速率>中度结冰，冰层快速增厚）：1. 立即脱离结冰条件—改变高度或航向 2. 机翼防冰+发动机防冰全部开启 3. 空速管加温—确认开 4. 注意：积冰增加重量+阻力+失速速度 5. 最小速度增加：结冰条件下VREF至少+5节 6. 不要放出减速板（结冰时减速板阻力可能不可控且可能损坏）7. 积冰严重影响襟翼效果—优先选襟翼30（而非40）着陆。",
      "triggers": ["ICING_CONDITION", "STALL"],
      "questions": [
        "严重积冰怎么办？",
        "结冰后着陆速度要加多少？",
        "积冰能放减速板吗？"
      ],
      "short_answer": "脱冰（变高度/航向）→全防冰开→空速管加温确认→VREF至少+5节→不放减速板→优先襟翼30着陆。积冰增加重量/阻力/失速速度。结冰中不放减速板防损坏。"
    }
  ]
}
